mathextras
