Metadata-Version: 1.0
Name: mathextras
Version: 2.0
Summary: Adds prime, lcm, and factors functionality.  
Home-page: https://github.com/Scoder12/mathextras
Author: Scoder12 and Poipt
Author-email: pymathextras@gmail.com
License: MIT
Platform: UNKNOWN
